xclip_json/__init__.py
xclip_json/main.py
xclip_json-0.1.0.dist-info/METADATA
xclip_json-0.1.0.dist-info/WHEEL
xclip_json-0.1.0.dist-info/entry_points.txt
xclip_json-0.1.0.dist-info/top_level.txt
xclip_json-0.1.0.dist-info/RECORD
