Metadata-Version: 2.4
Name: xclip-json
Version: 0.1.0
Summary: A command-line tool to dump X clipboard targets as JSON.
Author-email: "@readwithai" <talwrii@gmail.com>
Classifier: Programming Language :: Python :: 3
Classifier: License :: OSI Approved :: MIT License
Classifier: Operating System :: POSIX :: Linux
Requires-Python: >=3.7
